README.md
setup.cfg
setup.py
NextionEasy/__init__.py
NextionEasy/nextion_easy.py
NextionEasy.egg-info/PKG-INFO
NextionEasy.egg-info/SOURCES.txt
NextionEasy.egg-info/dependency_links.txt
NextionEasy.egg-info/not-zip-safe
NextionEasy.egg-info/top_level.txt