Metadata-Version: 2.1
Name: NextionEasy
Version: 1.1
Summary: Библиотека для получения и отправки данных на дисплей nextion
Home-page: UNKNOWN
Author-email: testerlzt@mail.ru
License: UNKNOWN
Platform: UNKNOWN
